pymetaf/__init__.py
pymetaf/parser.py
pymetaf-1.1.1.dist-info/licenses/LICENSE
tests/__init__.py
tests/test_metars.py
tests/test_validation.py
tests/case/__init__.py
tests/case/taf.py
tests/case/metar/__init__.py
tests/case/metar/get_field_text_case.py
tests/case/metar/parse_text_case.py
pymetaf-1.1.1.dist-info/METADATA
pymetaf-1.1.1.dist-info/WHEEL
pymetaf-1.1.1.dist-info/top_level.txt
pymetaf-1.1.1.dist-info/RECORD
