Metadata-Version: 2.4
Name: pymetaf
Version: 1.1.1
Summary: A python package for parsing metar & taf raw text
Home-page: https://github.com/Clarmy/pymetaf
Author: Wentao Li
Author-email: clarmyleewt@outlook.com
Classifier: Programming Language :: Python :: 3
Requires-Python: >=3.7
License-File: LICENSE
Requires-Dist: pytest
Dynamic: author
Dynamic: author-email
Dynamic: classifier
Dynamic: description
Dynamic: description-content-type
Dynamic: home-page
Dynamic: license-file
Dynamic: requires-dist
Dynamic: requires-python
Dynamic: summary
